{
  "items": [
    {
      "id": "30BA8766-A869-45A1-A56B-237C09FFED01",
      "deviceId": "Yilan-Loudong-0001",
      "shortLocation": "宜蘭縣羅東鎮",
      "address": "宜蘭縣羅東鎮公正路154號",
      "shakingReportNumber": 163,
      "deviceType": "mobile",
      "locationSponsor": {
        "links": [
          {
            "link": "https://g.co/kgs/HyDPD6r",
            "type": "others"
          }
        ],
        "name": "梁博文牙醫診所"
      },
      "createdAt": "2024-02-07T09:19:17Z",
      "installation": "normal",
      "uptimeMinute": 150358,
      "status": "active",
      "latitude": "24.787539",
      "earthquakeNumber": 2,
      "longitude": "121.800498",
      "deviceSponsor": {
        "links": [
          {
            "link": "https://g.co/kgs/HyDPD6r",
            "type": "others"
          }
        ],
        "name": "梁博文牙醫診所"
      },
      "activeRatio": 0.92,
      "inactiveRatio": 0.08,
      "shakingReportOneWeekPerDay": [
        0,
        4,
        0,
        7,
        8,
        10,
        3
      ]
    },
    {
      "id": "44462B61-5158-4D15-ABA9-BDF76618D4FB",
      "deviceId": "Yilan-Sanxing-0001",
      "shortLocation": "宜蘭縣三星鄉",
      "shakingReportNumber": 46,
      "address": "266宜蘭縣三星鄉尚貴路二段25號",
      "deviceType": "mobile",
      "locationSponsor": {
        "links": [
          {
            "link": "https://www.facebook.com/greenhorseland/",
            "type": "facebook"
          },
          {
            "type": "others",
            "link": "ghlss2022@gmail.com"
          }
        ],
        "name": "青青馬場"
      },
      "createdAt": "2024-03-13T10:32:29Z",
      "installation": "normal",
      "uptimeMinute": 100508,
      "status": "inactive",
      "latitude": "24.723672",
      "earthquakeNumber": 0,
      "longitude": "121.736284",
      "deviceSponsor": {
        "links": [
          {
            "link": "https://www.facebook.com/greenhorseland/",
            "type": "facebook"
          },
          {
            "type": "others",
            "link": "ghlss2022@gmail.com"
          }
        ],
        "name": "青青馬場"
      },
      "activeRatio": 0.95,
      "inactiveRatio": 0.05,
      "shakingReportOneWeekPerDay": [
        4,
        22,
        18,
        10,
        8,
        0,
        0
      ]
    },
    {
      "id": "1EF44D8C-5912-41F2-98AE-A66E303BB1D6",
      "deviceId": "Hualien-Hualien-0001",
      "shortLocation": "花蓮縣花蓮市",
      "shakingReportNumber": 48,
      "deviceType": "mobile",
      "locationSponsor": {
        "links": [
          {
            "link": "https://shop.vanger.com.tw",
            "type": "homepage"
          },
          {
            "type": "instagram",
            "link": "https://www.instagram.com/vangershoes/"
          },
          {
            "type": "line",
            "link": "https://page.line.me/?accountId=vangershoes&openerPlatform=native&openerKey=home%3Arecommend"
          },
          {
            "type": "facebook",
            "link": "https://www.facebook.com/vangermenshoes"
          }
        ],
        "name": "Vanger"
      },
      "createdAt": "2024-03-13T14:22:49Z",
      "installation": "normal",
      "uptimeMinute": 100397,
      "status": "inactive",
      "latitude": "24.658979",
      "earthquakeNumber": 0,
      "longitude": "121.823213",
      "deviceSponsor": {
        "links": [
          {
            "link": "https://shop.vanger.com.tw",
            "type": "homepage"
          },
          {
            "type": "instagram",
            "link": "https://www.instagram.com/vangershoes/"
          },
          {
            "type": "line",
            "link": "https://page.line.me/?accountId=vangershoes&openerPlatform=native&openerKey=home%3Arecommend"
          },
          {
            "type": "facebook",
            "link": "https://www.facebook.com/vangermenshoes"
          }
        ],
        "name": "Vanger"
      },
      "activeRatio": 0.95,
      "inactiveRatio": 0.05,
      "shakingReportOneWeekPerDay": [
        0,
        3,
        1,
        8,
        9,
        0,
        0
      ]
    },
    {
      "id": "2B3C4D5E-6789-0123-4567-890123456789",
      "deviceId": "Taipei-Xinyi-0001",
      "shortLocation": "台北市信義區",
      "address": "110台北市信義區信義路五段1號",
      "shakingReportNumber": 120,
      "deviceType": "mobile",
      "locationSponsor": {
        "links": [
          {
            "link": "https://www.ticc.com.tw/",
            "type": "homepage"
          },
          {
            "type": "facebook",
            "link": "https://www.facebook.com/ticcpage/?locale=zh_TW"
          }
        ],
        "name": "台北國際會議中心(TICC)"
      },
      "createdAt": "2024-01-15T10:00:00Z",
      "installation": "normal",
      "uptimeMinute": 178515,
      "status": "active",
      "latitude": "25.033964",
      "earthquakeNumber": 1,
      "longitude": "121.564468",
      "deviceSponsor": {
        "links": [
          {
            "link": "https://www.ticc.com.tw/",
            "type": "homepage"
          },
          {
            "type": "facebook",
            "link": "https://www.facebook.com/ticcpage/?locale=zh_TW"
          }
        ],
        "name": "台北國際會議中心(TICC)"
      },
      "activeRatio": 0.90,
      "inactiveRatio": 0.10,
      "shakingReportOneWeekPerDay": [
        5,
        4,
        6,
        3,
        7,
        2,
        1
      ]
    },
    {
      "id": "3C4D5E6F-7890-1234-5678-901234567890",
      "deviceId": "Taichung-NorthDistrict-0001",
      "shortLocation": "台中市北區",
      "address": "404台中市北區館前路1號",
      "shakingReportNumber": 95,
      "deviceType": "mobile",
      "locationSponsor": {
        "links": [
          {
            "link": "https://www.nmns.edu.tw/",
            "type": "homepage"
          },
          {
            "type": "facebook",
            "link": "https://www.facebook.com/nmnsTaiwan/?locale=zh_TW"
          }
        ],
        "name": "國立自然科學博物館"
      },
      "createdAt": "2024-02-10T14:00:00Z",
      "installation": "normal",
      "uptimeMinute": 145395,
      "status": "active",
      "latitude": "24.147736",
      "earthquakeNumber": 1,
      "longitude": "120.673648",
      "deviceSponsor": {
        "links": [
          {
            "link": "https://www.nmns.edu.tw/",
            "type": "homepage"
          },
          {
            "type": "facebook",
            "link": "https://www.facebook.com/nmnsTaiwan/?locale=zh_TW"
          }
        ],
        "name": "國立自然科學博物館"
      },
      "activeRatio": 0.91,
      "inactiveRatio": 0.09,
      "shakingReportOneWeekPerDay": [
        6,
        5,
        4,
        3,
        2,
        1,
        7
      ]
    },
    {
      "id": "4D5E6F7G-8901-2345-6789-012345678901",
      "deviceId": "Kaohsiung-Exhibition-0001",
      "shortLocation": "高雄市前鎮區",
      "address": "806高雄市前鎮區成功二路39號",
      "shakingReportNumber": 110,
      "deviceType": "mobile",
      "locationSponsor": {
        "links": [
          {
            "link": "http://www.kecc.com.tw/",
            "type": "homepage"
          },
          {
            "type": "facebook",
            "link": "https://www.facebook.com/kaohsiungexhibitioncenter/?locale=zh_TW"
          }
        ],
        "name": "高雄展覽館"
      },
      "createdAt": "2024-03-05T12:00:00Z",
      "installation": "normal",
      "uptimeMinute": 130275,
      "status": "active",
      "latitude": "22.612307",
      "earthquakeNumber": 2,
      "longitude": "120.306376",
      "deviceSponsor": {
        "links": [
          {
            "link": "http://www.kecc.com.tw/",
            "type": "homepage"
          },
          {
            "type": "facebook",
            "link": "https://www.facebook.com/kaohsiungexhibitioncenter/?locale=zh_TW"
          }
        ],
        "name": "高雄展覽館"
      },
      "activeRatio": 0.92,
      "inactiveRatio": 0.08,
      "shakingReportOneWeekPerDay": [
        7,
        6,
        5,
        4,
        3,
        2,
        1
      ]
    },
    {
      "id": "5E6F7G8H-9012-3456-7890-123456789012",
      "deviceId": "Hsinchu-SiliconTech-0001",
      "shakingReportNumber": 130,
      "shortLocation": "台中市烏日區",
      "address": "414台中市烏日區溪南路一段988巷296弄39號",
      "deviceType": "mobile",
      "locationSponsor": {
        "links": [
          {
            "link": "https://www.silicontech.com.tw",
            "type": "homepage"
          }
        ],
        "name": "矽品科技有限公司"
      },
      "createdAt": "2024-04-01T08:00:00Z",
      "installation": "normal",
      "uptimeMinute": 113235,
      "status": "active",
      "latitude": "24.784728",
      "earthquakeNumber": 2,
      "longitude": "120.993190",
      "deviceSponsor": {
        "links": [
          {
            "link": "https://www.silicontech.com.tw",
            "type": "homepage"
          }
        ],
        "name": "矽品科技有限公司"
      },
      "activeRatio": 0.93,
      "inactiveRatio": 0.07,
      "shakingReportOneWeekPerDay": [
        5,
        4,
        3,
        2,
        1,
        7,
        6
      ]
    },
    {
      "id": "6F7G8H9I-0123-4567-8901-234567890123",
      "deviceId": "Hualien-OceanPark-0001",
      "shakingReportNumber": 60,
      "shortLocation": "花蓮縣壽豐鄉",
      "address": "974花蓮縣壽豐鄉福德189號",
      "deviceType": "mobile",
      "locationSponsor": {
        "links": [
          {
            "link": "https://www.farglory-oceanpark.com.tw/",
            "type": "homepage"
          },
          {
            "type": "facebook",
            "link": "https://www.facebook.com/fargloryhop/?locale=zh_TW"
          }
        ],
        "name": "遠雄海洋公園"
      },
      "createdAt": "2024-01-20T10:00:00Z",
      "installation": "normal",
      "uptimeMinute": 171315,
      "status": "active",
      "latitude": "24.016824",
      "earthquakeNumber": 1,
      "longitude": "121.606371",
      "deviceSponsor": {
        "links": [
          {
            "link": "https://www.farglory-oceanpark.com.tw",
            "type": "homepage"
          },
          {
            "type": "facebook",
            "link": "https://www.facebook.com/fargloryhop/?locale=zh_TW"
          }
        ],
        "name": "遠雄海洋公園"
      },
      "activeRatio": 0.90,
      "inactiveRatio": 0.10,
      "shakingReportOneWeekPerDay": [
        4,
        3,
        2,
        1,
        7,
        6,
        5
      ]
    },
    {
      "id": "7G8H9I0J-1234-5678-9012-345678901234",
      "deviceId": "Tainan-ChimeiMuseum-0001",
      "shakingReportNumber": 140,
      "deviceType": "mobile",
      "shortLocation": "台南市仁德區",
      "address": "717台南市仁德區文華路二段66號",
      "locationSponsor": {
        "links": [
          {
            "link": "http://www.chimeimuseum.org/",
            "type": "homepage"
          },
          {
            "type": "facebook",
            "link": "https://www.facebook.com/chimeimuseum/?locale=zh_TW"
          }
        ],
        "name": "奇美博物館"
      },
      "createdAt": "2024-02-25T11:00:00Z",
      "installation": "normal",
      "uptimeMinute": 156195,
      "status": "active",
      "latitude": "22.967022",
      "earthquakeNumber": 2,
      "longitude": "120.205361",
      "deviceSponsor": {
        "links": [
          {
            "link": "http://www.chimeimuseum.org/",
            "type": "homepage"
          },
          {
            "type": "facebook",
            "link": "https://www.facebook.com/chimeimuseum/?locale=zh_TW"
          }
        ],
        "name": "奇美博物館"
      },
      "activeRatio": 0.94,
      "inactiveRatio": 0.06,
      "shakingReportOneWeekPerDay": [
        3,
        2,
        1,
        7,
        6,
        5,
        4
      ]
    },
    {
      "id": "8H9I0J1K-2345-6789-0123-456789012345",
      "deviceId": "Yunlin-Janhusun-0001",
      "shakingReportNumber": 100,
      "deviceType": "mobile",
      "shortLocation": "雲林縣古坑鄉",
      "address": "646雲林縣古坑鄉67號",
      "createdAt": "2024-03-15T09:00:00Z",
      "installation": "normal",
      "uptimeMinute": 136275,
      "status": "active",
      "latitude": "23.508906",
      "earthquakeNumber": 1,
      "longitude": "120.815140",
      "deviceSponsor": {
        "links": [
          {
            "link": "http://janfusun.com.tw/fancyworld.php",
            "type": "homepage"
          },
          {
            "type": "facebook",
            "link": "https://www.facebook.com/janfusun0/?locale=zh_TW"
          }
        ],
        "name": "劍湖山世界主題樂園"
      },
      "activeRatio": 0.92,
      "inactiveRatio": 0.08,
      "shakingReportOneWeekPerDay": [
        2,
        1,
        7,
        6,
        5,
        4,
        3
      ]
    },
    {
      "id": "9I0J1K2L-3456-7890-1234-567890123456",
      "deviceId": "Taoyuan-Xpark-0001",
      "shakingReportNumber": 85,
      "deviceType": "mobile",
      "shortLocation": "桃園市中壢區",
      "address": "320桃園市中壢區春德路105號",
      "locationSponsor": {
        "links": [
          {
            "link": "https://www.xpark.com.tw/",
            "type": "homepage"
          },
          {
            "type": "facebook",
            "link": "https://www.facebook.com/Xparkaquarium/?locale=zh_TW"
          }
        ],
        "name": "Xpark"
      },
      "createdAt": "2024-04-10T14:00:00Z",
      "installation": "normal",
      "uptimeMinute": 107595,
      "status": "active",
      "latitude": "25.077250",
      "earthquakeNumber": 2,
      "longitude": "121.223055",
      "deviceSponsor": {
        "links": [
          {
            "link": "https://www.xpark.com.tw/",
            "type": "homepage"
          },
          {
            "type": "facebook",
            "link": "https://www.facebook.com/Xparkaquarium/?locale=zh_TW"
          }
        ],
        "name": "Xpark"
      },
      "activeRatio": 0.93,
      "inactiveRatio": 0.07,
      "shakingReportOneWeekPerDay": [
        7,
        6,
        5,
        4,
        3,
        2,
        1
      ]
    },
    {
      "id": "0J1K2L3M-4567-8901-2345-678901234567",
      "deviceId": "Miaoli-HSRStation-0001",
      "shakingReportNumber": 75,
      "deviceType": "mobile",
      "locationSponsor": {
        "links": [
          {
            "link": "http://www.thsrc.com.tw/tw/StationInfo/Prospect/E8FC2123-2AAF-46FF-AD79-51D4002A1EF3",
            "type": "homepage"
          }
        ],
        "name": "高鐵苗栗站"
      },
      "createdAt": "2024-01-30T08:00:00Z",
      "installation": "normal",
      "uptimeMinute": 166275,
      "status": "active",
      "latitude": "24.612133",
      "earthquakeNumber": 2,
      "longitude": "120.816644",
      "shortLocation": "苗栗縣後龍鎮",
      "address": "356苗栗縣後龍鎮高鐵三路268號",
      "activeRatio": 0.91,
      "inactiveRatio": 0.09,
      "shakingReportOneWeekPerDay": [
        6,
        5,
        4,
        3,
        2,
        1,
        7
      ]
    }
  ]
}
